LICENSE
MANIFEST.in
README.md
setup.cfg
setup.py
sphinx_aimms_theme/AIMMSDomain.py
sphinx_aimms_theme/AIMMSLexer.py
sphinx_aimms_theme/AIMMSspellingFilters.py
sphinx_aimms_theme/__init__.py
sphinx_aimms_theme/breadcrumbs.html
sphinx_aimms_theme/footer.html
sphinx_aimms_theme/layout.html
sphinx_aimms_theme/searchbox.html
sphinx_aimms_theme/spelling_wordlist.txt
sphinx_aimms_theme/theme.conf
sphinx_aimms_theme.egg-info/PKG-INFO
sphinx_aimms_theme.egg-info/SOURCES.txt
sphinx_aimms_theme.egg-info/dependency_links.txt
sphinx_aimms_theme.egg-info/entry_points.txt
sphinx_aimms_theme.egg-info/requires.txt
sphinx_aimms_theme.egg-info/top_level.txt
sphinx_aimms_theme/static/AIMMS_logo_BlackWhite-PRINT-900x508.jpg
sphinx_aimms_theme/static/AIMMS_logo_H_RGB.png
sphinx_aimms_theme/static/AIMMS_logo_S_RGB.png
sphinx_aimms_theme/static/copycode.js
sphinx_aimms_theme/static/favicon.ico
sphinx_aimms_theme/static/aimms_css/styles.css
sphinx_aimms_theme/static/icons/100.jpg
sphinx_aimms_theme/static/icons/105.png
sphinx_aimms_theme/static/icons/11.png
sphinx_aimms_theme/static/icons/110.png
sphinx_aimms_theme/static/icons/111.png
sphinx_aimms_theme/static/icons/12.png
sphinx_aimms_theme/static/icons/13.png
sphinx_aimms_theme/static/icons/14.png
sphinx_aimms_theme/static/icons/140.png
sphinx_aimms_theme/static/icons/141.png
sphinx_aimms_theme/static/icons/145.png
sphinx_aimms_theme/static/icons/15 (1).png
sphinx_aimms_theme/static/icons/15.png
sphinx_aimms_theme/static/icons/150.png
sphinx_aimms_theme/static/icons/152.png
sphinx_aimms_theme/static/icons/16.png
sphinx_aimms_theme/static/icons/160.png
sphinx_aimms_theme/static/icons/161.png
sphinx_aimms_theme/static/icons/162.png
sphinx_aimms_theme/static/icons/163.png
sphinx_aimms_theme/static/icons/168.png
sphinx_aimms_theme/static/icons/170.png
sphinx_aimms_theme/static/icons/172.png
sphinx_aimms_theme/static/icons/175.png
sphinx_aimms_theme/static/icons/176.png
sphinx_aimms_theme/static/icons/180.png
sphinx_aimms_theme/static/icons/181.png
sphinx_aimms_theme/static/icons/200.png
sphinx_aimms_theme/static/icons/201.png
sphinx_aimms_theme/static/icons/202.png
sphinx_aimms_theme/static/icons/203.png
sphinx_aimms_theme/static/icons/204.png
sphinx_aimms_theme/static/icons/205.png
