Metadata-Version: 2.1
Name: sphinx-aimms-theme
Version: 0.1.42
Summary: AIMMS theme for Sphinx
Home-page: https://github.com/aimms/sphinx-aimms-theme
Author: AIMMS User Support
Author-email: support@aimms.com
License: MIT
Platform: UNKNOWN
License-File: LICENSE
